{
  "channelUrl": "https://www.youtube.com/@ShoonyaShikharGurukulam",
  "categories": [
    {
      "id": "campus",
      "en": { "name": "Campus Life" },
      "hi": { "name": "परिसर जीवन" },
      "images": [
        {
          "id": "c1",
          "type": "image",
          "showOnHero": true,
          "src": "https://res.cloudinary.com/dgzi1ruvs/image/upload/v1780139966/campus_outside_ct1ej1.jpg",
          "en": "Main Temple",
          "hi": "मुख्य मंदिर"
        },
        {
          "id": "hero-1",
          "type": "image",
          "showOnHero": true,
          "src": "https://res.cloudinary.com/dgzi1ruvs/image/upload/v1780139976/news_channel_banner_with_students_tfho1b.jpg",
          "en": "Gurukulam Students News Channel Feature",
          "hi": "गुरुकुल छात्र समाचार चैनल विशेष प्रसारण"
        },
        {
          "id": "hero-2",
          "type": "image",
          "showOnHero": true,
          "src": "https://res.cloudinary.com/dgzi1ruvs/image/upload/v1780139977/banner_with_students_axuv4u.jpg",
          "en": "Traditional Education Campus Banner",
          "hi": "पारंपरिक शिक्षा परिसर मुख्य बैनर"
        }
      ]
    },
    {
      "id": "yoga",
      "en": { "name": "Yoga & Meditation" },
      "hi": { "name": "योग और ध्यान" },
      "images": [
        {
          "id": "y2",
          "type": "video",
          "showOnHero": true,
          "src": "https://res.cloudinary.com/dgzi1ruvs/video/upload/WhatsApp_Video_2026-06-07_at_4.51.02_PM_egj2pi.mp4",
          "en": "Dhyan Sadhana Guide",
          "hi": "ध्यान साधना मार्गदर्शन"
        },
        {
          "id": "y3",
          "type": "image",
          "showOnHero": false,
          "src": "https://res.cloudinary.com/dgzi1ruvs/image/upload/v1780139968/stasang1_ltlkyu.jpg",
          "en": "Satsang & Traditional Wisdom Assembly",
          "hi": "सत्संग एवं पारंपरिक ज्ञान सभा"
        }
      ]
    },
    {
      "id": "martial-arts",
      "en": { "name": "Martial Arts" },
      "hi": { "name": "मार्शल आर्ट" },
      "images": [
        {
          "id": "m1",
          "type": "image",
          "src": "https://res.cloudinary.com/dgzi1ruvs/image/upload/v1780843917/2_n4nnqw.jpg",
          "en": "Self Defense Students",
          "hi": "आत्मरक्षा सीखने वाले छात्र"
        },
        {
          "id": "m2",
          "type": "video",
          "showOnHero": true,
          "src": "https://res.cloudinary.com/dgzi1ruvs/video/upload/WhatsApp_Video_2026-06-07_at_11.41.03_AM_1_lcxhdn.mp4",
          "en": "Self Defense Practice",
          "hi": "आत्मरक्षा अभ्यास"
        }
      ]
    },
    {
      "id": "festivals",
      "en": { "name": "Celebrations" },
      "hi": { "name": "उत्सव एवं पर्व" },
      "images": [
        {
          "id": "f2",
          "type": "image",
          "showOnHero": true,
          "src": "https://res.cloudinary.com/dgzi1ruvs/image/upload/v1780139967/inauguration1_ksuhvo.jpg",
          "en": "Gurukulam Campus Inauguration Ceremony",
          "hi": "गुरुकुलम् परिसर उद्घाटन पावन समारोह"
        },
        {
          "id": "f3",
          "type": "video",
          "showOnHero": true,
          "src": "https://res.cloudinary.com/dgzi1ruvs/video/upload/youtube_news_channel_video_tupmem.mp4",
          "en": "Official Media News Coverage",
          "hi": "आधिकारिक मीडिया समाचार कवेरेज"
        }
      ]
    }
  ]
}
